zarame/__init__.py
zarame/dump.py
zarame/load.py
zarame/utils.py
zarame-0.0.2.dist-info/DESCRIPTION.rst
zarame-0.0.2.dist-info/METADATA
zarame-0.0.2.dist-info/RECORD
zarame-0.0.2.dist-info/WHEEL
zarame-0.0.2.dist-info/metadata.json
zarame-0.0.2.dist-info/top_level.txt
