Metadata-Version: 2.0
Name: zarame
Version: 0.0.2
Summary: Simple structural transducer using NamedTuple
Home-page: https://github.com/pistatium/zarame
Author: pistatium
License: UNKNOWN
Platform: UNKNOWN
Provides-Extra: test
Provides-Extra: test
Requires-Dist: pytest; extra == 'test'
